MANIFEST.in
README.md
setup.cfg
setup.py
versioneer.py
asyncfileserver/__init__.py
asyncfileserver/_version.py
asyncfileserver.egg-info/PKG-INFO
asyncfileserver.egg-info/SOURCES.txt
asyncfileserver.egg-info/dependency_links.txt
asyncfileserver.egg-info/entry_points.txt
asyncfileserver.egg-info/requires.txt
asyncfileserver.egg-info/top_level.txt
asyncfileserver/app/__init__.py
asyncfileserver/app/main.py
asyncfileserver/infra/__init__.py
asyncfileserver/infra/async_console_input.py
asyncfileserver/infra/async_console_output.py
asyncfileserver/infra/file.py
asyncfileserver/model/__init__.py
asyncfileserver/model/ask_answer_arbiter.py
asyncfileserver/model/client.py
asyncfileserver/model/confirm_command.py
asyncfileserver/model/confirm_command_factory.py
asyncfileserver/model/confirm_put_queue.py
asyncfileserver/model/simple_queue.py
asyncfileserver/model/view_data.py
asyncfileserver/model/view_data_factory.py
asyncfileserver/tests/__init__.py
asyncfileserver/tests/unit/__init__.py
asyncfileserver/tests/unit/app/__init__.py
asyncfileserver/tests/unit/infra/__init__.py
asyncfileserver/tests/unit/infra/buffer_output.py
asyncfileserver/tests/unit/infra/queue_input.py
asyncfileserver/tests/unit/infra/test_async_console_input.py
asyncfileserver/tests/unit/infra/test_async_console_output.py
asyncfileserver/tests/unit/infra/test_file.py
asyncfileserver/tests/unit/model/__init__.py
asyncfileserver/tests/unit/model/fake_async_queue.py
asyncfileserver/tests/unit/model/test_ask_answer_arbiter.py
asyncfileserver/tests/unit/model/test_client.py
asyncfileserver/tests/unit/model/test_confirm_command_factory.py
asyncfileserver/tests/unit/model/test_confirm_put_queue.py
asyncfileserver/tests/unit/model/test_simple_queue.py
asyncfileserver/tests/unit/model/test_view_data_factory.py