Metadata-Version: 2.1
Name: asyncfileserver
Version: 0.2.0
Summary: File Server
Home-page: https://github.com/tarc/asyncfileserver
Author: Tarcísio Genaro Rodrigues
Author-email: tarcisio.genaro@gmail.com
License: UNKNOWN
Download-URL: https://github.com/tarc/asyncfileserver/archive/v0.0.1.tar.gz
Project-URL: Bug Reports, https://github.com/pypa/sampleproject/issues
Project-URL: Funding, https://donate.pypi.org
Project-URL: Say Thanks!, http://saythanks.io/to/example
Project-URL: Source, https://github.com/pypa/sampleproject/
Platform: UNKNOWN
Classifier: Development Status :: 1 - Planning
Classifier: Intended Audience :: Information Technology
Classifier: Topic :: Communications :: File Sharing
Classifier: License :: OSI Approved :: MIT License
Classifier: Programming Language :: Python :: 3.7
Requires-Python: >=3.7
Provides-Extra: dev
